crepes_weighted/__init__.py
crepes_weighted/base.py
crepes_weighted/extras.py
crepes_weighted-0.1.3.dist-info/LICENSE
crepes_weighted-0.1.3.dist-info/METADATA
crepes_weighted-0.1.3.dist-info/WHEEL
crepes_weighted-0.1.3.dist-info/top_level.txt
crepes_weighted-0.1.3.dist-info/RECORD
