Metadata-Version: 2.2
Name: crepes_weighted
Version: 0.1.3
Summary: Weighted version of crepes: Conformal classifiers, regressors, and predictive systems (crepes)
Home-page: https://github.com/predict-idlab/crepes-weighted
Author: Jef Jonkers
Author-email: jef.jonkers@ugent.be
Classifier: Programming Language :: Python :: 3
Classifier: License :: OSI Approved :: BSD License
Classifier: Operating System :: OS Independent
Requires-Python: >=3.8
License-File: LICENSE
Requires-Dist: numpy
Requires-Dist: pandas
Dynamic: author
Dynamic: author-email
Dynamic: classifier
Dynamic: description
Dynamic: description-content-type
Dynamic: home-page
Dynamic: requires-dist
Dynamic: requires-python
Dynamic: summary
